README.md
setup.py
ros/__init__.py
ros/fun.py
ros/main.py
ros/maths.py
ros/roserrors.py
ros/secure.py
ros/string.py
ros/system.py
ros/time.py
ros/web.py
ros_code_modules.egg-info/PKG-INFO
ros_code_modules.egg-info/SOURCES.txt
ros_code_modules.egg-info/dependency_links.txt
ros_code_modules.egg-info/requires.txt
ros_code_modules.egg-info/top_level.txt