Metadata-Version: 2.1
Name: ros-code-modules
Version: 2.0.0.23
Summary: A Python module/library containing lots of tools to simplify Python development.
Home-page: https://github.com/Richienb/ROS-Code
Author: Richie Bendall
Author-email: richiebendall@gmail.com
License: UNKNOWN
Platform: UNKNOWN
Classifier: Development Status :: 4 - Beta
Classifier: Intended Audience :: Developers
Classifier: License :: OSI Approved :: Apache Software License
Classifier: Natural Language :: English
Classifier: Programming Language :: Python
Classifier: Operating System :: OS Independent
Classifier: Topic :: Software Development :: Libraries :: Python Modules
